LFSR_8bit.vhdl
library IEEE;
use IEEE.STD_LOGIC_1164.ALL;
use IEEE.NUMERIC_STD.ALL;

entity LFSR_8bit is
    port (
        clk       : in  std_logic;
        rst       : in  std_logic;
        enable    : in  std_logic;
        load_seed : in  std_logic;
        seed      : in  std_logic_vector(7 downto 0);
        out_val   : out std_logic_vector(7 downto 0)
    );
end LFSR_8bit;

architecture rtl of LFSR_8bit is
    signal reg : std_logic_vector(7 downto 0);
begin
    process(clk, rst)
    begin
        if rst = '1' then
            reg <= (others => '0');
        elsif rising_edge(clk) then
            if load_seed = '1' then
                reg <= seed;
            elsif enable = '1' then
                -- taps em bits 7, 5, 4, 3
                reg <= reg(6 downto 0) & (reg(7) xor reg(5) xor reg(4) xor reg(3));
            end if;
        end if;
    end process;

    out_val <= reg;
end rtl;

tb_LFSR.vhdl
library IEEE;
use IEEE.STD_LOGIC_1164.ALL;
use IEEE.NUMERIC_STD.ALL;

entity tb_LFSR is
end tb_LFSR;

architecture sim of tb_LFSR is
    constant CLK_PERIOD : time := 10 ns;

    signal clk       : std_logic := '0';
    signal rst       : std_logic := '1';
    signal enable    : std_logic := '0';
    signal load_seed : std_logic := '0';
    signal seed      : std_logic_vector(7 downto 0) := x"AD";
    signal out_val   : std_logic_vector(7 downto 0);
begin
    uut: entity work.LFSR_8bit
        port map (
            clk       => clk,
            rst       => rst,
            enable    => enable,
            load_seed => load_seed,
            seed      => seed,
            out_val   => out_val
        );

    -- Clock
    clk_process : process
    begin
        while true loop
            clk <= '0';
            wait for CLK_PERIOD / 2;
            clk <= '1';
            wait for CLK_PERIOD / 2;
        end loop;
    end process;

    -- Estímulos
    stim_proc: process
    begin
        rst <= '1';
        wait for 20 ns;
        rst <= '0';

        load_seed <= '1';
        wait for CLK_PERIOD;
        load_seed <= '0';

        enable <= '1';
        wait for 200 ns;

        enable <= '0';
        wait for 20 ns;

        report "Simulação finalizada com sucesso!" severity note;
        wait for 10 ns;
        wait;
    end process;
end sim;

wave.vcd
$date
  Sun Nov  9 15:10:25 2025
$end
$version
  GHDL v0
$end
$timescale
  1 fs
$end
$scope module standard $end
$upscope $end
$scope module std_logic_1164 $end
$upscope $end
$scope module numeric_std $end
$upscope $end
$scope module tb_lfsr $end
$var reg 1 ! clk $end
$var reg 1 " rst $end
$var reg 1 # enable $end
$var reg 1 $ load_seed $end
$var reg 8 % seed[7:0] $end
$var reg 8 & out_val[7:0] $end
$scope module uut $end
$var reg 1 ' clk $end
$var reg 1 ( rst $end
$var reg 1 ) enable $end
$var reg 1 * load_seed $end
$var reg 8 + seed[7:0] $end
$var reg 8 , out_val[7:0] $end
$var reg 8 - reg[7:0] $end
$upscope $end
$upscope $end
$enddefinitions $end
#0
0!
1"
0#
0$
b10101101 %
b00000000 &
0'
1(
0)
0*
b10101101 +
b00000000 ,
b00000000 -
#5000000
1!
1'
#10000000
0!
0'
#15000000
1!
1'
#20000000
0!
0"
1$
0'
0(
1*
#25000000
1!
b10101101 &
1'
b10101101 ,
b10101101 -
#30000000
0!
1#
0$
0'
1)
0*
#35000000
1!
b01011011 &
1'
b01011011 ,
b01011011 -
#40000000
0!
0'
#45000000
1!
b10110110 &
1'
b10110110 ,
b10110110 -
#50000000
0!
0'
#55000000
1!
b01101101 &
1'
b01101101 ,
b01101101 -
#60000000
0!
0'
#65000000
1!
b11011010 &
1'
b11011010 ,
b11011010 -
#70000000
0!
0'
#75000000
1!
b10110101 &
1'
b10110101 ,
b10110101 -
#80000000
0!
0'
#85000000
1!
b01101011 &
1'
b01101011 ,
b01101011 -
#90000000
0!
0'
#95000000
1!
b11010110 &
1'
b11010110 ,
b11010110 -
#100000000
0!
0'
#105000000
1!
b10101100 &
1'
b10101100 ,
b10101100 -
#110000000
0!
0'
#115000000
1!
b01011001 &
1'
b01011001 ,
b01011001 -
#120000000
0!
0'
#125000000
1!
b10110010 &
1'
b10110010 ,
b10110010 -
#130000000
0!
0'
#135000000
1!
b01100101 &
1'
b01100101 ,
b01100101 -
#140000000
0!
0'
#145000000
1!
b11001011 &
1'
b11001011 ,
b11001011 -
#150000000
0!
0'
#155000000
1!
b10010110 &
1'
b10010110 ,
b10010110 -
#160000000
0!
0'
#165000000
1!
b00101100 &
1'
b00101100 ,
b00101100 -
#170000000
0!
0'
#175000000
1!
b01011000 &
1'
b01011000 ,
b01011000 -
#180000000
0!
0'
#185000000
1!
b10110000 &
1'
b10110000 ,
b10110000 -
#190000000
0!
0'
#195000000
1!
b01100001 &
1'
b01100001 ,
b01100001 -
#200000000
0!
0'
#205000000
1!
b11000011 &
1'
b11000011 ,
b11000011 -
#210000000
0!
0'
#215000000
1!
b10000111 &
1'
b10000111 ,
b10000111 -
#220000000
0!
0'
#225000000
1!
b00001111 &
1'
b00001111 ,
b00001111 -
#230000000
0!
0#
0'
0)
