Input.vhdl
library IEEE;
use IEEE.STD_LOGIC_1164.ALL;
use IEEE.NUMERIC_STD.ALL;

entity Input is
    Port (
        clk : in STD_LOGIC;
        reset : in STD_LOGIC;
        inicia_Input : in STD_LOGIC;
        sw : in STD_LOGIC_VECTOR(6 downto 0);
        ativado : out STD_LOGIC_VECTOR(2 downto 0)
    );
end Input;

architecture Behavioral of Input is
    signal sw_anterior : STD_LOGIC_VECTOR(6 downto 0) := (others => '0');
    signal sw_atual : STD_LOGIC_VECTOR(6 downto 0) := (others => '0');
    
begin
    process(clk, reset)
    begin
        if reset = '1' then
            sw_anterior <= (others => '0');
            sw_atual <= (others => '0');
            ativado <= "000";
            
        elsif rising_edge(clk) then
            if inicia_Input = '1' then
                -- Atualiza registradores
                sw_anterior <= sw_atual;
                sw_atual <= sw;
                
                -- Detecta QUALQUER mudança e identifica qual switch foi ativado
                if (sw_atual /= sw_anterior) then
                    -- Verifica qual bit mudou de 0 para 1
                    for i in 0 to 6 loop
                        if sw_atual(i) = '1' and sw_anterior(i) = '0' then
                            -- Converte posição do switch para código 3 bits
                            case i is
                                when 0 => ativado <= "001";  -- SW0
                                when 1 => ativado <= "010";  -- SW1
                                when 2 => ativado <= "011";  -- SW2
                                when 3 => ativado <= "100";  -- SW3
                                when 4 => ativado <= "101";  -- SW4
                                when 5 => ativado <= "110";  -- SW5
                                when 6 => ativado <= "111";  -- SW6
                                when others => ativado <= "000";
                            end case;
                            exit;  -- Pega apenas o primeiro switch ativado
                        end if;
                    end loop;
                else
                    ativado <= "000";  -- Nenhuma mudança
                end if;
            else
                -- Reset quando não está capturando
                ativado <= "000";
                sw_anterior <= (others => '0');
                sw_atual <= (others => '0');
            end if;
        end if;
    end process;

end Behavioral;

Controller.vhdl
library IEEE;
use IEEE.STD_LOGIC_1164.ALL;
use IEEE.NUMERIC_STD.ALL;

entity Controller is
    Port (
        clk : in STD_LOGIC;
        reset : in STD_LOGIC;
        start : in STD_LOGIC;
        sw_usuario : in STD_LOGIC_VECTOR(6 downto 0);
        ativado : in STD_LOGIC_VECTOR(2 downto 0);
        sw_out : out STD_LOGIC_VECTOR(6 downto 0);
        inicia_Input : out STD_LOGIC
    );
end Controller;

architecture Behavioral of Controller is
    -- Tipo para armazenar a sequência do usuário
    type array_resposta is array (0 to 6) of std_logic_vector(2 downto 0);
    signal resposta_usuario : array_resposta;
    
    -- Máquina de estados
    type estado_type is (AGUARDA_START, CAPTURANDO, COMPLETO);
    signal estado : estado_type := AGUARDA_START;
    
    -- Contador de inputs recebidos
    signal contador_inputs : integer range 0 to 7 := 0;
    
    -- Sinais de debug
    signal debug_resposta_0, debug_resposta_1, debug_resposta_2 : std_logic_vector(2 downto 0);
    signal debug_resposta_3, debug_resposta_4, debug_resposta_5, debug_resposta_6 : std_logic_vector(2 downto 0);
    
begin
    -- Conexões de debug
    debug_resposta_0 <= resposta_usuario(0);
    debug_resposta_1 <= resposta_usuario(1);
    debug_resposta_2 <= resposta_usuario(2);
    debug_resposta_3 <= resposta_usuario(3);
    debug_resposta_4 <= resposta_usuario(4);
    debug_resposta_5 <= resposta_usuario(5);
    debug_resposta_6 <= resposta_usuario(6);

    process(clk, reset)
    begin
        if reset = '1' then
            estado <= AGUARDA_START;
            contador_inputs <= 0;
            inicia_Input <= '0';
            sw_out <= (others => '0');
            -- Limpa array de resposta
            for i in 0 to 6 loop
                resposta_usuario(i) <= "000";
            end loop;
            
        elsif rising_edge(clk) then
            -- Passa os switches do usuário direto para o input
            sw_out <= sw_usuario;
            
            case estado is
                when AGUARDA_START =>
                    inicia_Input <= '0';
                    contador_inputs <= 0;
                    if start = '1' then
                        estado <= CAPTURANDO;
                        inicia_Input <= '1';
                    end if;
                    
                when CAPTURANDO =>
                    inicia_Input <= '1';
                    
                    -- Quando recebe um novo input do módulo Input
                    if ativado /= "000" then
                        -- Armazena no array na ordem de chegada
                        resposta_usuario(contador_inputs) <= ativado;
                        contador_inputs <= contador_inputs + 1;
                        
                        -- Verifica se já recebeu todos os 7 inputs
                        if contador_inputs = 6 then
                            estado <= COMPLETO;
                            inicia_Input <= '0';
                        end if;
                    end if;
                    
                when COMPLETO =>
                    inicia_Input <= '0';
                    -- Permanece neste estado até reset
                    if reset = '1' then
                        estado <= AGUARDA_START;
                    end if;
                    
            end case;
        end if;
    end process;

end Behavioral;

tb_Controller.vhdl
library IEEE;
use IEEE.STD_LOGIC_1164.ALL;
use IEEE.NUMERIC_STD.ALL;

entity tb_Controller is
end tb_Controller;

architecture Behavioral of tb_Controller is
    component Controller
        Port (
            clk : in STD_LOGIC;
            reset : in STD_LOGIC;
            start : in STD_LOGIC;
            sw_usuario : in STD_LOGIC_VECTOR(6 downto 0);
            ativado : in STD_LOGIC_VECTOR(2 downto 0);
            sw_out : out STD_LOGIC_VECTOR(6 downto 0);
            inicia_Input : out STD_LOGIC
        );
    end component;
    
    component Input
        Port (
            clk : in STD_LOGIC;
            reset : in STD_LOGIC;
            inicia_Input : in STD_LOGIC;
            sw : in STD_LOGIC_VECTOR(6 downto 0);
            ativado : out STD_LOGIC_VECTOR(2 downto 0)
        );
    end component;
    
    signal clk : STD_LOGIC := '0';
    signal reset : STD_LOGIC := '1';
    signal start : STD_LOGIC := '0';
    signal sw_usuario : STD_LOGIC_VECTOR(6 downto 0) := (others => '0');
    signal ativado : STD_LOGIC_VECTOR(2 downto 0);
    signal sw_out : STD_LOGIC_VECTOR(6 downto 0);
    signal inicia_Input : STD_LOGIC;
    
    constant CLK_PERIOD : time := 10 ns;
    
begin
    -- Controller (DUT principal)
    dut_controller: Controller
    port map (
        clk => clk,
        reset => reset,
        start => start,
        sw_usuario => sw_usuario,
        ativado => ativado,
        sw_out => sw_out,
        inicia_Input => inicia_Input
    );
    
    -- Input (conectado à saída da controller)
    dut_input: Input
    port map (
        clk => clk,
        reset => reset,
        inicia_Input => inicia_Input,
        sw => sw_out,  -- Recebe switches da controller
        ativado => ativado  -- Envia para controller
    );
    
    -- Clock
    clk <= not clk after CLK_PERIOD/2;
    
    process
    begin
        -- Reset
        reset <= '1';
        wait for 50 ns;
        reset <= '0';
        wait for 50 ns;
        
        -- Inicia captura
        report "=== Iniciando captura com START ===";
        start <= '1';
        wait for 30 ns;
        start <= '0';
        wait for 50 ns;
        
        -- Simula usuário ativando switches em ordem
        report "Usuario ativa: SW2";
        sw_usuario <= "0000100";  -- SW2
        wait for 100 ns;
        report "Ativado detectado: " & integer'image(to_integer(unsigned(ativado)));
        
        report "Usuario ativa: SW5";
        sw_usuario <= "0010100";  -- SW2 + SW5
        wait for 100 ns;
        report "Ativado detectado: " & integer'image(to_integer(unsigned(ativado)));
        
        report "Usuario ativa: SW1";
        sw_usuario <= "0010110";  -- SW2 + SW5 + SW1
        wait for 100 ns;
        report "Ativado detectado: " & integer'image(to_integer(unsigned(ativado)));
        
        report "Usuario ativa: SW0";
        sw_usuario <= "0010111";  -- SW2 + SW5 + SW1 + SW0
        wait for 100 ns;
        report "Ativado detectado: " & integer'image(to_integer(unsigned(ativado)));
        
        report "Usuario ativa: SW6";
        sw_usuario <= "1010111";  -- SW2 + SW5 + SW1 + SW0 + SW6
        wait for 100 ns;
        report "Ativado detectado: " & integer'image(to_integer(unsigned(ativado)));
        
        report "Usuario ativa: SW4";
        sw_usuario <= "1011111";  -- SW2 + SW5 + SW1 + SW0 + SW6 + SW4
        wait for 100 ns;
        report "Ativado detectado: " & integer'image(to_integer(unsigned(ativado)));
        
        report "Usuario ativa: SW3";
        sw_usuario <= "1111111";  -- Todos (SW3 por último)
        wait for 100 ns;
        report "Ativado detectado: " & integer'image(to_integer(unsigned(ativado)));
        
        wait for 200 ns;
        assert false report "=== Teste Controller concluido ===" severity note;
        wait;
    end process;
end Behavioral;

wave_controller.vcd
$date
  Fri Nov 14 18:26:00 2025
$end
$version
  GHDL v0
$end
$timescale
  1 fs
$end
$scope module standard $end
$upscope $end
$scope module std_logic_1164 $end
$upscope $end
$scope module numeric_std $end
$upscope $end
$scope module tb_controller $end
$var reg 1 ! clk $end
$var reg 1 " reset $end
$var reg 1 # start $end
$var reg 7 $ sw_usuario[6:0] $end
$var reg 3 % ativado[2:0] $end
$var reg 7 & sw_out[6:0] $end
$var reg 1 ' inicia_input $end
$scope module dut_controller $end
$var reg 1 ( clk $end
$var reg 1 ) reset $end
$var reg 1 * start $end
$var reg 7 + sw_usuario[6:0] $end
$var reg 3 , ativado[2:0] $end
$var reg 7 - sw_out[6:0] $end
$var reg 1 . inicia_input $end
$comment resposta_usuario is not handled $end
$comment estado is not handled $end
$var integer 32 / contador_inputs $end
$var reg 3 0 debug_resposta_0[2:0] $end
$var reg 3 1 debug_resposta_1[2:0] $end
$var reg 3 2 debug_resposta_2[2:0] $end
$var reg 3 3 debug_resposta_3[2:0] $end
$var reg 3 4 debug_resposta_4[2:0] $end
$var reg 3 5 debug_resposta_5[2:0] $end
$var reg 3 6 debug_resposta_6[2:0] $end
$upscope $end
$scope module dut_input $end
$var reg 1 7 clk $end
$var reg 1 8 reset $end
$var reg 1 9 inicia_input $end
$var reg 7 : sw[6:0] $end
$var reg 3 ; ativado[2:0] $end
$var reg 7 < sw_anterior[6:0] $end
$var reg 7 = sw_atual[6:0] $end
$upscope $end
$upscope $end
$enddefinitions $end
#0
0!
1"
0#
b0000000 $
b000 %
b0000000 &
0'
0(
1)
0*
b0000000 +
b000 ,
b0000000 -
0.
b0 /
b000 0
b000 1
b000 2
b000 3
b000 4
b000 5
b000 6
07
18
09
b0000000 :
b000 ;
b0000000 <
b0000000 =
#5000000
1!
1(
17
#10000000
0!
0(
07
#15000000
1!
1(
17
#20000000
0!
0(
07
#25000000
1!
1(
17
#30000000
0!
0(
07
#35000000
1!
1(
17
#40000000
0!
0(
07
#45000000
1!
1(
17
#50000000
0!
0"
0(
0)
07
08
#55000000
1!
1(
17
#60000000
0!
0(
07
#65000000
1!
1(
17
#70000000
0!
0(
07
#75000000
1!
1(
17
#80000000
0!
0(
07
#85000000
1!
1(
17
#90000000
0!
0(
07
#95000000
1!
1(
17
#100000000
0!
1#
0(
1*
07
#105000000
1!
1'
1(
1.
17
19
#110000000
0!
0(
07
#115000000
1!
1(
17
#120000000
0!
0(
07
#125000000
1!
1(
17
#130000000
0!
0#
0(
0*
07
#135000000
1!
1(
17
#140000000
0!
0(
07
#145000000
1!
1(
17
#150000000
0!
0(
07
#155000000
1!
1(
17
#160000000
0!
0(
07
#165000000
1!
1(
17
#170000000
0!
0(
07
#175000000
1!
1(
17
#180000000
0!
b0000100 $
0(
b0000100 +
07
#185000000
1!
b0000100 &
1(
b0000100 -
17
b0000100 :
#190000000
0!
0(
07
#195000000
1!
1(
17
b0000100 =
#200000000
0!
0(
07
#205000000
1!
b011 %
1(
b011 ,
17
b011 ;
b0000100 <
#210000000
0!
0(
07
#215000000
1!
b000 %
1(
b000 ,
b1 /
b011 0
17
b000 ;
#220000000
0!
0(
07
#225000000
1!
1(
17
#230000000
0!
0(
07
#235000000
1!
1(
17
#240000000
0!
0(
07
#245000000
1!
1(
17
#250000000
0!
0(
07
#255000000
1!
1(
17
#260000000
0!
0(
07
#265000000
1!
1(
17
#270000000
0!
0(
07
#275000000
1!
1(
17
#280000000
0!
b0010100 $
0(
b0010100 +
07
#285000000
1!
b0010100 &
1(
b0010100 -
17
b0010100 :
#290000000
0!
0(
07
#295000000
1!
1(
17
b0010100 =
#300000000
0!
0(
07
#305000000
1!
b101 %
1(
b101 ,
17
b101 ;
b0010100 <
#310000000
0!
0(
07
#315000000
1!
b000 %
1(
b000 ,
b10 /
b101 1
17
b000 ;
#320000000
0!
0(
07
#325000000
1!
1(
17
#330000000
0!
0(
07
#335000000
1!
1(
17
#340000000
0!
0(
07
#345000000
1!
1(
17
#350000000
0!
0(
07
#355000000
1!
1(
17
#360000000
0!
0(
07
#365000000
1!
1(
17
#370000000
0!
0(
07
#375000000
1!
1(
17
#380000000
0!
b0010110 $
0(
b0010110 +
07
#385000000
1!
b0010110 &
1(
b0010110 -
17
b0010110 :
#390000000
0!
0(
07
#395000000
1!
1(
17
b0010110 =
#400000000
0!
0(
07
#405000000
1!
b010 %
1(
b010 ,
17
b010 ;
b0010110 <
#410000000
0!
0(
07
#415000000
1!
b000 %
1(
b000 ,
b11 /
b010 2
17
b000 ;
#420000000
0!
0(
07
#425000000
1!
1(
17
#430000000
0!
0(
07
#435000000
1!
1(
17
#440000000
0!
0(
07
#445000000
1!
1(
17
#450000000
0!
0(
07
#455000000
1!
1(
17
#460000000
0!
0(
07
#465000000
1!
1(
17
#470000000
0!
0(
07
#475000000
1!
1(
17
#480000000
0!
b0010111 $
0(
b0010111 +
07
#485000000
1!
b0010111 &
1(
b0010111 -
17
b0010111 :
#490000000
0!
0(
07
#495000000
1!
1(
17
b0010111 =
#500000000
0!
0(
07
#505000000
1!
b001 %
1(
b001 ,
17
b001 ;
b0010111 <
#510000000
0!
0(
07
#515000000
1!
b000 %
1(
b000 ,
b100 /
b001 3
17
b000 ;
#520000000
0!
0(
07
#525000000
1!
1(
17
#530000000
0!
0(
07
#535000000
1!
1(
17
#540000000
0!
0(
07
#545000000
1!
1(
17
#550000000
0!
0(
07
#555000000
1!
1(
17
#560000000
0!
0(
07
#565000000
1!
1(
17
#570000000
0!
0(
07
#575000000
1!
1(
17
#580000000
0!
b1010111 $
0(
b1010111 +
07
#585000000
1!
b1010111 &
1(
b1010111 -
17
b1010111 :
#590000000
0!
0(
07
#595000000
1!
1(
17
b1010111 =
#600000000
0!
0(
07
#605000000
1!
b111 %
1(
b111 ,
17
b111 ;
b1010111 <
#610000000
0!
0(
07
#615000000
1!
b000 %
1(
b000 ,
b101 /
b111 4
17
b000 ;
#620000000
0!
0(
07
#625000000
1!
1(
17
#630000000
0!
0(
07
#635000000
1!
1(
17
#640000000
0!
0(
07
#645000000
1!
1(
17
#650000000
0!
0(
07
#655000000
1!
1(
17
#660000000
0!
0(
07
#665000000
1!
1(
17
#670000000
0!
0(
07
#675000000
1!
1(
17
#680000000
0!
b1011111 $
0(
b1011111 +
07
#685000000
1!
b1011111 &
1(
b1011111 -
17
b1011111 :
#690000000
0!
0(
07
#695000000
1!
1(
17
b1011111 =
#700000000
0!
0(
07
#705000000
1!
b100 %
1(
b100 ,
17
b100 ;
b1011111 <
#710000000
0!
0(
07
#715000000
1!
b000 %
1(
b000 ,
b110 /
b100 5
17
b000 ;
#720000000
0!
0(
07
#725000000
1!
1(
17
#730000000
0!
0(
07
#735000000
1!
1(
17
#740000000
0!
0(
07
#745000000
1!
1(
17
#750000000
0!
0(
07
#755000000
1!
1(
17
#760000000
0!
0(
07
#765000000
1!
1(
17
#770000000
0!
0(
07
#775000000
1!
1(
17
#780000000
0!
b1111111 $
0(
b1111111 +
07
#785000000
1!
b1111111 &
1(
b1111111 -
17
b1111111 :
#790000000
0!
0(
07
#795000000
1!
1(
17
b1111111 =
#800000000
0!
0(
07
#805000000
1!
b110 %
1(
b110 ,
17
b110 ;
b1111111 <
#810000000
0!
0(
07
#815000000
1!
b000 %
0'
1(
b000 ,
0.
b111 /
b110 6
17
09
b000 ;
#820000000
0!
0(
07
#825000000
1!
1(
17
b0000000 <
b0000000 =
