Gerador_Aleatorio.vhdl
library IEEE;
use IEEE.STD_LOGIC_1164.ALL;
use IEEE.NUMERIC_STD.ALL;
use work.Types.all;

-- =====================================================
-- 🌱 Seed Generator
-- =====================================================
entity Seed_generator is
    Port ( 
        clk       : in std_logic;
        rst       : in std_logic;
        start     : in std_logic;
        save_seed : in std_logic;
        seed      : out std_logic_vector(2 downto 0)
    );
end Seed_generator;

architecture rtl of Seed_generator is
    signal lfsr_r    : std_logic_vector(2 downto 0);
    signal saved_seed : std_logic_vector(2 downto 0);
begin
    process(clk, rst)
        variable newbit : std_logic;
        variable next_state : std_logic_vector(2 downto 0);
    begin
        if rst = '1' then
            lfsr_r <= "001";
            saved_seed <= "001";
        elsif rising_edge(clk) then
            if save_seed = '1' then
                newbit := lfsr_r(2) xor lfsr_r(0);
                next_state := newbit & lfsr_r(2 downto 1);
                lfsr_r <= next_state;
                report "Seed_generator: LFSR avançado para " & 
                       integer'image(to_integer(unsigned(next_state)));
            end if;

            if start = '1' then
                if lfsr_r = "000" then
                    saved_seed <= "110";
                    report "SEED CAPTURADA COM PROTECAO: 0 -> 110";
                else
                    saved_seed <= lfsr_r;
                    report "SEED CAPTURADA: " & 
                           integer'image(to_integer(unsigned(lfsr_r)));
                end if;
            end if;
        end if;
    end process;
    seed <= saved_seed;
end rtl;

-- =====================================================
-- 🔄 LFSR 3 bits
-- =====================================================
library IEEE;
use IEEE.STD_LOGIC_1164.ALL;
use IEEE.NUMERIC_STD.ALL;
use work.Types.all;

entity LFSR_3bits is
    port (
        clk                 : in std_logic;
        rst                 : in std_logic;
        enable_lfsr         : in std_logic;
        load_seed           : in std_logic;
        seed                : in std_logic_vector(2 downto 0);
        indice_vector       : out array_3X7bits;
        indice_vector_ready : out std_logic
    );
end LFSR_3bits;

architecture rtl of LFSR_3bits is
    signal reg : std_logic_vector(2 downto 0) := "001";
    signal results : array_3X7bits := (others => "000");
    signal count : integer range 0 to 7 := 0;
    signal running : std_logic := '0';
    signal prev_enable : std_logic := '0';
begin
    process(clk, rst)
        variable temp : std_logic_vector(2 downto 0);
        variable newbit : std_logic;
    begin
        if rst = '1' then
            reg <= "001";
            results <= (others => "000");
            count <= 0;
            running <= '0';
            prev_enable <= '0';
            indice_vector_ready <= '0';
        elsif rising_edge(clk) then
            prev_enable <= enable_lfsr;
            indice_vector_ready <= '0';

            if enable_lfsr = '1' and prev_enable = '0' then
                running <= '1';
                count <= 0;
                results(0) <= reg;
            end if;

            if load_seed = '1' then
                if seed /= "000" then
                    reg <= seed;
                else
                    reg <= "001";
                end if;
            elsif running = '1' then
                newbit := reg(2) xor reg(1);
                temp := reg(1 downto 0) & newbit;
                reg <= temp;
                if count < 6 then
                    count <= count + 1;
                    results(count + 1) <= temp;
                else
                    running <= '0';
                    indice_vector_ready <= '1';
                end if;
            end if;
        end if;
    end process;
    indice_vector <= results;
end rtl;

-- =====================================================
-- 🔀 Reorder Vector
-- =====================================================
library IEEE;
use IEEE.STD_LOGIC_1164.ALL;
use IEEE.NUMERIC_STD.ALL;
use work.Types.all;

entity Reorder_Vector is
    Port (
        clk           : in std_logic;
        rst           : in std_logic;
        enable        : in std_logic;
        indice_vector : in array_3X7bits;
        random_vector : out array_3X7bits;
        ready         : out std_logic
    );
end Reorder_Vector;

architecture Behavioral of Reorder_Vector is
    constant BASE_ORIGINAL : array_3X7bits := ("001", "010", "011", "100", "101", "110", "111");
    signal current_base : array_3X7bits := BASE_ORIGINAL;
    signal cycle_count : integer range 0 to 7 := 0;
    signal ready_int : std_logic := '0';
    signal backup_base : array_3X7bits := BASE_ORIGINAL;
    signal backup_count : integer range 0 to 7 := 0;
begin
    process(clk)
        variable new_base : array_3X7bits;
        variable index : integer;
    begin
        if rising_edge(clk) then
            if rst = '1' then
                current_base <= backup_base;
                cycle_count <= backup_count;
                ready_int <= '0';
                report "Reorder_Vector: RESET - restaurando backup (cycle_count = " & integer'image(backup_count) & ")";
            else
                ready_int <= '0';
                if enable = '1' then
                    for i in 0 to 6 loop
                        index := to_integer(unsigned(indice_vector(i))) - 1;
                        if index >= 0 and index <= 6 then
                            new_base(i) := current_base(index);
                        else
                            new_base(i) := "000";
                        end if;
                    end loop;
                    
                    random_vector <= new_base;
                    ready_int <= '1';
                    current_base <= new_base;
                    backup_base <= new_base;
                    
                    if cycle_count = 6 then
                        cycle_count <= 0;
                        backup_count <= 0;
                        report "Reorder_Vector: CICLO COMPLETO - resetando para BASE_ORIGINAL";
                    else
                        cycle_count <= cycle_count + 1;
                        backup_count <= backup_count + 1;
                        report "Reorder_Vector: Operacao " & integer'image(cycle_count + 1) & "/7 - base ATUALIZADO e salvo no BACKUP";
                    end if;
                end if;
            end if;
        end if;
    end process;
    ready <= ready_int;
end Behavioral;

-- =====================================================
-- 🎯 Sequence Design (Sistema Completo)
-- =====================================================
library IEEE;
use IEEE.STD_LOGIC_1164.ALL;
use IEEE.NUMERIC_STD.ALL;
use work.Types.all;

entity Sequence_design is
    Port (
        clk       : in std_logic;
        rst       : in std_logic;
        start     : in std_logic;
        base_out  : out array_3X7bits;
        ready_out : out std_logic
    );
end Sequence_design;

architecture wiring of Sequence_design is
    signal seed              : std_logic_vector(2 downto 0);
    signal seed_ready_ctrl   : std_logic;
    signal load_seed         : std_logic;
    signal enable_lfsr       : std_logic;
    signal indice_vector     : array_3X7bits;
    signal indice_ready      : std_logic;
    signal random_vector     : array_3X7bits;
    signal reorder_ready     : std_logic;
begin
    u_controller: entity work.Controller
        port map (
            clk           => clk,
            rst           => rst,
            start         => start,
            indice_ready  => indice_ready,
            reorder_ready => reorder_ready,
            seed_ready    => seed_ready_ctrl,
            load_seed     => load_seed,
            enable_lfsr   => enable_lfsr,
            global_ready  => ready_out
        );

    u_seed: entity work.Seed_generator
        port map (
            clk       => clk,
            rst       => rst,
            start     => load_seed,
            save_seed => seed_ready_ctrl,
            seed      => seed
        );

    u_lfsr: entity work.LFSR_3bits
        port map (
            clk                 => clk,
            rst                 => rst,
            enable_lfsr         => enable_lfsr,
            load_seed           => load_seed,
            seed                => seed,
            indice_vector       => indice_vector,
            indice_vector_ready => indice_ready
        );

    u_reorder: entity work.Reorder_Vector
        port map (
            clk           => clk,
            rst           => rst,
            enable        => indice_ready,
            indice_vector => indice_vector,
            random_vector => random_vector,
            ready         => reorder_ready
        );

    base_out <= random_vector;
end wiring;

Controller.vhdl
library IEEE;
use IEEE.STD_LOGIC_1164.ALL;
use IEEE.NUMERIC_STD.ALL;

-- Package para tipos personalizados
package Types is
    type array_3X7bits is array (0 to 6) of std_logic_vector(2 downto 0);
end package Types;

package body Types is
end package body Types;

library IEEE;
use IEEE.STD_LOGIC_1164.ALL;
use work.Types.all;

entity Controller is
    Port ( 
        clk           : in std_logic;
        rst           : in std_logic;
        start         : in std_logic;
        seed_ready    : out std_logic;
        indice_ready  : in std_logic;
        reorder_ready : in std_logic;
        load_seed     : out std_logic;
        enable_lfsr   : out std_logic;
        global_ready  : out std_logic
    );
end Controller;

architecture Behavioral of Controller is
    type state_type is (S_IDLE, S_LOAD_SEED, S_RUN_LFSR, S_REORDER, S_DONE);
    signal state : state_type := S_IDLE;
    signal prev_start : std_logic := '0';
    
begin
    process(clk, rst)
    begin
        if rst = '1' then
            state <= S_IDLE;
            seed_ready <= '0';
            load_seed <= '0';
            enable_lfsr <= '0';
            global_ready <= '0';
            prev_start <= '0';
        elsif rising_edge(clk) then
            prev_start <= start;
            
            -- Valores padrão
            load_seed <= '0';
            enable_lfsr <= '0';
            global_ready <= '0';
            seed_ready <= '0';
            
            case state is
                when S_IDLE =>
                    if start = '1' and prev_start = '0' then
                        state <= S_LOAD_SEED;
                        load_seed <= '1';
                        seed_ready <= '1';
                        report "Controller: Capturando seed atual";
                    end if;
                    
                when S_LOAD_SEED =>
                    state <= S_RUN_LFSR;
                    enable_lfsr <= '1';
                    report "Controller: Iniciando LFSR principal";
                    
                when S_RUN_LFSR =>
                    enable_lfsr <= '1';
                    if indice_ready = '1' then
                        state <= S_REORDER;
                        report "Controller: LFSR terminou, iniciando reordenamento";
                    end if;
                    
                when S_REORDER =>
                    if reorder_ready = '1' then
                        state <= S_DONE;
                        report "Controller: Reordenamento concluído";
                    end if;
                    
                when S_DONE =>
                    global_ready <= '1';
                    seed_ready <= '1';
                    report "Controller: Processamento completo";
                    if start = '0' then
                        state <= S_IDLE;
                    end if;
            end case;
        end if;
    end process;
end Behavioral;

tb_Sequence_design.vhdl
library IEEE;
use IEEE.STD_LOGIC_1164.ALL;
use IEEE.NUMERIC_STD.ALL;
use work.Types.all;

entity tb_Sequence_design is
end tb_Sequence_design;

architecture behavior of tb_Sequence_design is
    -- Constantes
    constant CLK_PERIOD : time := 10 ns;
    
    -- Sinais do DUT
    signal clk       : std_logic := '0';
    signal rst       : std_logic := '0';
    signal start     : std_logic := '0';
    signal base_out  : array_3X7bits;
    signal ready_out : std_logic;
    
    -- Controle de simulação
    signal simulation_running : boolean := true;
    
begin
    -- =====================================================
    -- DUT (Design Under Test)
    -- =====================================================
    DUT: entity work.Sequence_design
        port map (
            clk       => clk,
            rst       => rst,
            start     => start,
            base_out  => base_out,
            ready_out => ready_out
        );

    -- =====================================================
    -- Geração de Clock
    -- =====================================================
    clk_process : process
    begin
        while simulation_running loop
            clk <= '0';
            wait for CLK_PERIOD/2;
            clk <= '1';
            wait for CLK_PERIOD/2;
        end loop;
        wait;
    end process;

    -- =====================================================
    -- Processo de Estímulos
    -- =====================================================
    stim_proc : process
        procedure apply_reset is
        begin
            report "Aplicando RESET...";
            rst <= '1';
            wait for CLK_PERIOD * 2;
            rst <= '0';
            wait for CLK_PERIOD;
        end procedure;
        
        procedure start_sequence is
        begin
            report " Iniciando sequencia...";
            start <= '1';
            wait for CLK_PERIOD;
            start <= '0';
            wait until ready_out = '1';
            wait for CLK_PERIOD;
            report "Sequencia completada!";
        end procedure;
        
        procedure print_vector(vector_name : string; vector : array_3X7bits) is
        begin
            report vector_name & ": " &
                   integer'image(to_integer(unsigned(vector(0)))) & " " &
                   integer'image(to_integer(unsigned(vector(1)))) & " " &
                   integer'image(to_integer(unsigned(vector(2)))) & " " &
                   integer'image(to_integer(unsigned(vector(3)))) & " " &
                   integer'image(to_integer(unsigned(vector(4)))) & " " &
                   integer'image(to_integer(unsigned(vector(5)))) & " " &
                   integer'image(to_integer(unsigned(vector(6))));
        end procedure;
        
    begin
        report " ===========================================" severity note;
        report " Iniciando Testbench do Sequence Design" severity note;
        report " ===========================================" severity note;
        
        -- Reset inicial
        apply_reset;
        
        -- Aguarda estabilização
        wait for CLK_PERIOD * 5;
        
        -- =====================================================
        -- TESTE 1: Primeira execução
        -- =====================================================
        report "TESTE 1: Primeira execucao apos reset" severity note;
        start_sequence;
        print_vector("Vetor de saida 1", base_out);
        wait for CLK_PERIOD * 10;
        
        -- =====================================================
        -- TESTE 2: Segunda execução (seed diferente)
        -- =====================================================
        report "TESTE 2: Segunda execucao" severity note;
        start_sequence;
        print_vector("Vetor de saida 2", base_out);
        wait for CLK_PERIOD * 10;
        
        -- =====================================================
        -- TESTE 3: Terceira execução
        -- =====================================================
        report "TESTE 3: Terceira execucao" severity note;
        start_sequence;
        print_vector("Vetor de saida 3", base_out);
        wait for CLK_PERIOD * 10;
        
        -- =====================================================
        -- TESTE 4: Reset e nova execução
        -- =====================================================
        report "TESTE 4: Reset e nova execucao" severity note;
        apply_reset;
        wait for CLK_PERIOD * 5;
        start_sequence;
        print_vector("Vetor de saida apos reset", base_out);
        wait for CLK_PERIOD * 10;
        
        -- =====================================================
        -- TESTE 5: Múltiplas execuções rápidas
        -- =====================================================
        report "TESTE 5: Execucoes consecutivas" severity note;
        for i in 1 to 3 loop
            start_sequence;
            print_vector("Vetor execucao " & integer'image(i), base_out);
            wait for CLK_PERIOD * 5;
        end loop;
        
        -- =====================================================
        -- TESTE 6: Verificação de ready_out
        -- =====================================================
        report "TESTE 6: Verificação do sinal ready_out" severity note;
        start <= '1';
        wait for CLK_PERIOD;
        start <= '0';
        
        -- Monitora ready_out
        wait until ready_out = '1';
        report "ready_out detectado - sistema pronto!" severity note;
        print_vector("Vetor final", base_out);
        
        -- Aguarda e finaliza
        wait for CLK_PERIOD * 20;
        
        report " ===========================================" severity note;
        report " Testbench concluido com sucesso!" severity note;
        report " ===========================================" severity note;
        
        simulation_running <= false;
        wait;
    end process;

    -- =====================================================
    -- Processo de Monitoramento
    -- =====================================================
    monitor_proc : process(clk)
        variable start_count : integer := 0;
        variable ready_count : integer := 0;
    begin
        if rising_edge(clk) then
            -- Monitora pulso de start
            if start = '1' then
                start_count := start_count + 1;
                report "START detectado - total: " & integer'image(start_count);
            end if;
            
            -- Monitora ready_out
            if ready_out'event and ready_out = '1' then
                ready_count := ready_count + 1;
                report "READY_OUT detectado - total: " & integer'image(ready_count);
            end if;
        end if;
    end process;

    -- =====================================================
    -- Verificação de Assertions
    -- =====================================================
    assertions_proc : process
    begin
        -- Verifica se ready_out nunca fica ativo por mais de 1 ciclo consecutivo
        wait until ready_out = '1';
        wait for CLK_PERIOD;
        assert ready_out = '0' 
            report "ERRO: ready_out ativo por mais de 1 ciclo!" 
            severity error;
        
        -- Verifica se o vetor de saída não contém valores inválidos
        for i in 0 to 6 loop
            wait until base_out'event;
            assert base_out(i) /= "000" and base_out(i) /= "UUU"
                report "ERRO: Valor inválido no vetor de saida: " & 
                       integer'image(to_integer(unsigned(base_out(i))))
                severity error;
        end loop;
        
        wait;
    end process;

end behavior;

wave.vcd
$date
  Sun Nov 16 00:23:35 2025
$end
$version
  GHDL v0
$end
$timescale
  1 fs
$end
$scope module standard $end
$upscope $end
$scope module std_logic_1164 $end
$upscope $end
$scope module numeric_std $end
$upscope $end
$scope module types $end
$upscope $end
$scope module tb_sequence_design $end
$var reg 1 ! clk $end
$var reg 1 " rst $end
$var reg 1 # start $end
$comment base_out is not handled $end
$var reg 1 $ ready_out $end
$var reg 1 % simulation_running $end
$scope module dut $end
$var reg 1 & clk $end
$var reg 1 ' rst $end
$var reg 1 ( start $end
$comment base_out is not handled $end
$var reg 1 ) ready_out $end
$var reg 3 * seed[2:0] $end
$var reg 1 + seed_ready_ctrl $end
$var reg 1 , load_seed $end
$var reg 1 - enable_lfsr $end
$comment indice_vector is not handled $end
$var reg 1 . indice_ready $end
$comment random_vector is not handled $end
$var reg 1 / reorder_ready $end
$scope module u_controller $end
$var reg 1 0 clk $end
$var reg 1 1 rst $end
$var reg 1 2 start $end
$var reg 1 3 seed_ready $end
$var reg 1 4 indice_ready $end
$var reg 1 5 reorder_ready $end
$var reg 1 6 load_seed $end
$var reg 1 7 enable_lfsr $end
$var reg 1 8 global_ready $end
$comment state is not handled $end
$var reg 1 9 prev_start $end
$upscope $end
$scope module u_seed $end
$var reg 1 : clk $end
$var reg 1 ; rst $end
$var reg 1 < start $end
$var reg 1 = save_seed $end
$var reg 3 > seed[2:0] $end
$var reg 3 ? lfsr_r[2:0] $end
$var reg 3 @ saved_seed[2:0] $end
$upscope $end
$scope module u_lfsr $end
$var reg 1 A clk $end
$var reg 1 B rst $end
$var reg 1 C enable_lfsr $end
$var reg 1 D load_seed $end
$var reg 3 E seed[2:0] $end
$comment indice_vector is not handled $end
$var reg 1 F indice_vector_ready $end
$var reg 3 G reg[2:0] $end
$comment results is not handled $end
$var integer 32 H count $end
$var reg 1 I running $end
$var reg 1 J prev_enable $end
$upscope $end
$scope module u_reorder $end
$var reg 1 K clk $end
$var reg 1 L rst $end
$var reg 1 M enable $end
$comment indice_vector is not handled $end
$comment random_vector is not handled $end
$var reg 1 N ready $end
$comment current_base is not handled $end
$var integer 32 O cycle_count $end
$var reg 1 P ready_int $end
$comment backup_base is not handled $end
$var integer 32 Q backup_count $end
$upscope $end
$upscope $end
$upscope $end
$enddefinitions $end
#0
0!
1"
0#
0$
1%
0&
1'
0(
0)
b001 *
0+
0,
0-
0.
0/
00
11
02
03
04
05
06
07
08
09
0:
1;
0<
0=
b001 >
b001 ?
b001 @
0A
1B
0C
0D
b001 E
0F
b001 G
b0 H
0I
0J
0K
1L
0M
0N
b0 O
0P
b0 Q
#5000000
1!
1&
10
1:
1A
1K
#10000000
0!
0&
00
0:
0A
0K
#15000000
1!
1&
10
1:
1A
1K
#20000000
0!
0"
0&
0'
00
01
0:
0;
0A
0B
0K
0L
#25000000
1!
1&
10
1:
1A
1K
#30000000
0!
0&
00
0:
0A
0K
#35000000
1!
1&
10
1:
1A
1K
#40000000
0!
0&
00
0:
0A
0K
#45000000
1!
1&
10
1:
1A
1K
#50000000
0!
0&
00
0:
0A
0K
#55000000
1!
1&
10
1:
1A
1K
#60000000
0!
0&
00
0:
0A
0K
#65000000
1!
1&
10
1:
1A
1K
#70000000
0!
0&
00
0:
0A
0K
#75000000
1!
1&
10
1:
1A
1K
#80000000
0!
1#
0&
1(
00
12
0:
0A
0K
#85000000
1!
1&
1+
1,
10
13
16
19
1:
1<
1=
1A
1D
1K
#90000000
0!
0#
0&
0(
00
02
0:
0A
0K
#95000000
1!
1&
0+
0,
1-
10
03
06
17
09
1:
0<
0=
b100 ?
1A
1C
0D
1K
#100000000
0!
0&
00
0:
0A
0K
#105000000
1!
1&
10
17
1:
1A
1I
1J
1K
#110000000
0!
0&
00
0:
0A
0K
#115000000
1!
1&
10
17
1:
1A
b010 G
b1 H
1K
#120000000
0!
0&
00
0:
0A
0K
#125000000
1!
1&
10
17
1:
1A
b101 G
b10 H
1K
#130000000
0!
0&
00
0:
0A
0K
#135000000
1!
1&
10
17
1:
1A
b011 G
b11 H
1K
#140000000
0!
0&
00
0:
0A
0K
#145000000
1!
1&
10
17
1:
1A
b111 G
b100 H
1K
#150000000
0!
0&
00
0:
0A
0K
#155000000
1!
1&
10
17
1:
1A
b110 G
b101 H
1K
#160000000
0!
0&
00
0:
0A
0K
#165000000
1!
1&
10
17
1:
1A
b100 G
b110 H
1K
#170000000
0!
0&
00
0:
0A
0K
#175000000
1!
1&
1.
10
14
17
1:
1A
1F
b001 G
0I
1K
1M
#180000000
0!
0&
00
0:
0A
0K
#185000000
1!
1&
0.
1/
10
04
15
17
1:
1A
0F
1K
0M
1N
b1 O
1P
b1 Q
#190000000
0!
0&
00
0:
0A
0K
#195000000
1!
1&
0-
0/
10
05
07
1:
1A
0C
1K
0N
0P
#200000000
0!
0&
00
0:
0A
0K
#205000000
1!
1$
1&
1)
1+
10
13
18
1:
1=
1A
0J
1K
#210000000
0!
0&
00
0:
0A
0K
#215000000
1!
0$
1&
0)
0+
10
03
08
1:
0=
b110 ?
1A
1K
#220000000
0!
0&
00
0:
0A
0K
#225000000
1!
1&
10
1:
1A
1K
#230000000
0!
0&
00
0:
0A
0K
#235000000
1!
1&
10
1:
1A
1K
#240000000
0!
0&
00
0:
0A
0K
#245000000
1!
1&
10
1:
1A
1K
#250000000
0!
0&
00
0:
0A
0K
#255000000
1!
1&
10
1:
1A
1K
#260000000
0!
0&
00
0:
0A
0K
#265000000
1!
1&
10
1:
1A
1K
#270000000
0!
0&
00
0:
0A
0K
#275000000
1!
1&
10
1:
1A
1K
#280000000
0!
0&
00
0:
0A
0K
#285000000
1!
1&
10
1:
1A
1K
#290000000
0!
0&
00
0:
0A
0K
#295000000
1!
1&
10
1:
1A
1K
#300000000
0!
0&
00
0:
0A
0K
#305000000
1!
1&
10
1:
1A
1K
#310000000
0!
0&
00
0:
0A
0K
#315000000
1!
1#
1&
1(
1+
1,
10
12
13
16
19
1:
1<
1=
1A
1D
1K
#320000000
0!
0&
00
0:
0A
0K
#325000000
1!
0#
1&
0(
b110 *
0+
0,
1-
10
02
03
06
17
09
1:
0<
0=
b110 >
b111 ?
b110 @
1A
1C
0D
b110 E
1K
#330000000
0!
0&
00
0:
0A
0K
#335000000
1!
1&
10
17
1:
1A
b0 H
1I
1J
1K
#340000000
0!
0&
00
0:
0A
0K
#345000000
1!
1&
10
17
1:
1A
b010 G
b1 H
1K
#350000000
0!
0&
00
0:
0A
0K
#355000000
1!
1&
10
17
1:
1A
b101 G
b10 H
1K
#360000000
0!
0&
00
0:
0A
0K
#365000000
1!
1&
10
17
1:
1A
b011 G
b11 H
1K
#370000000
0!
0&
00
0:
0A
0K
#375000000
1!
1&
10
17
1:
1A
b111 G
b100 H
1K
#380000000
0!
0&
00
0:
0A
0K
#385000000
1!
1&
10
17
1:
1A
b110 G
b101 H
1K
#390000000
0!
0&
00
0:
0A
0K
#395000000
1!
1&
10
17
1:
1A
b100 G
b110 H
1K
#400000000
0!
0&
00
0:
0A
0K
#405000000
1!
1&
1.
10
14
17
1:
1A
1F
b001 G
0I
1K
1M
#410000000
0!
0&
00
0:
0A
0K
#415000000
1!
1&
0.
1/
10
04
15
17
1:
1A
0F
1K
0M
1N
b10 O
1P
b10 Q
#420000000
0!
0&
00
0:
0A
0K
#425000000
1!
1&
0-
0/
10
05
07
1:
1A
0C
1K
0N
0P
#430000000
0!
0&
00
0:
0A
0K
#435000000
1!
1$
1&
1)
1+
10
13
18
1:
1=
1A
0J
1K
#440000000
0!
0&
00
0:
0A
0K
#445000000
1!
0$
1&
0)
0+
10
03
08
1:
0=
b011 ?
1A
1K
#450000000
0!
0&
00
0:
0A
0K
#455000000
1!
1&
10
1:
1A
1K
#460000000
0!
0&
00
0:
0A
0K
#465000000
1!
1&
10
1:
1A
1K
#470000000
0!
0&
00
0:
0A
0K
#475000000
1!
1&
10
1:
1A
1K
#480000000
0!
0&
00
0:
0A
0K
#485000000
1!
1&
10
1:
1A
1K
#490000000
0!
0&
00
0:
0A
0K
#495000000
1!
1&
10
1:
1A
1K
#500000000
0!
0&
00
0:
0A
0K
#505000000
1!
1&
10
1:
1A
1K
#510000000
0!
0&
00
0:
0A
0K
#515000000
1!
1&
10
1:
1A
1K
#520000000
0!
0&
00
0:
0A
0K
#525000000
1!
1&
10
1:
1A
1K
#530000000
0!
0&
00
0:
0A
0K
#535000000
1!
1&
10
1:
1A
1K
#540000000
0!
0&
00
0:
0A
0K
#545000000
1!
1#
1&
1(
1+
1,
10
12
13
16
19
1:
1<
1=
1A
1D
1K
#550000000
0!
0&
00
0:
0A
0K
#555000000
1!
0#
1&
0(
b011 *
0+
0,
1-
10
02
03
06
17
09
1:
0<
0=
b011 >
b101 ?
b011 @
1A
1C
0D
b011 E
b110 G
1K
#560000000
0!
0&
00
0:
0A
0K
#565000000
1!
1&
10
17
1:
1A
b0 H
1I
1J
1K
#570000000
0!
0&
00
0:
0A
0K
#575000000
1!
1&
10
17
1:
1A
b100 G
b1 H
1K
#580000000
0!
0&
00
0:
0A
0K
#585000000
1!
1&
10
17
1:
1A
b001 G
b10 H
1K
#590000000
0!
0&
00
0:
0A
0K
#595000000
1!
1&
10
17
1:
1A
b010 G
b11 H
1K
#600000000
0!
0&
00
0:
0A
0K
#605000000
1!
1&
10
17
1:
1A
b101 G
b100 H
1K
#610000000
0!
0&
00
0:
0A
0K
#615000000
1!
1&
10
17
1:
1A
b011 G
b101 H
1K
#620000000
0!
0&
00
0:
0A
0K
#625000000
1!
1&
10
17
1:
1A
b111 G
b110 H
1K
#630000000
0!
0&
00
0:
0A
0K
#635000000
1!
1&
1.
10
14
17
1:
1A
1F
b110 G
0I
1K
1M
#640000000
0!
0&
00
0:
0A
0K
#645000000
1!
1&
0.
1/
10
04
15
17
1:
1A
0F
1K
0M
1N
b11 O
1P
b11 Q
#650000000
0!
0&
00
0:
0A
0K
#655000000
1!
1&
0-
0/
10
05
07
1:
1A
0C
1K
0N
0P
#660000000
0!
0&
00
0:
0A
0K
#665000000
1!
1$
1&
1)
1+
10
13
18
1:
1=
1A
0J
1K
#670000000
0!
0&
00
0:
0A
0K
#675000000
1!
0$
1&
0)
0+
10
03
08
1:
0=
b010 ?
1A
1K
#680000000
0!
0&
00
0:
0A
0K
#685000000
1!
1&
10
1:
1A
1K
#690000000
0!
0&
00
0:
0A
0K
#695000000
1!
1&
10
1:
1A
1K
#700000000
0!
0&
00
0:
0A
0K
#705000000
1!
1&
10
1:
1A
1K
#710000000
0!
0&
00
0:
0A
0K
#715000000
1!
1&
10
1:
1A
1K
#720000000
0!
0&
00
0:
0A
0K
#725000000
1!
1&
10
1:
1A
1K
#730000000
0!
0&
00
0:
0A
0K
#735000000
1!
1&
10
1:
1A
1K
#740000000
0!
0&
00
0:
0A
0K
#745000000
1!
1&
10
1:
1A
1K
#750000000
0!
0&
00
0:
0A
0K
#755000000
1!
1&
10
1:
1A
1K
#760000000
0!
0&
00
0:
0A
0K
#765000000
1!
1&
10
1:
1A
1K
#770000000
0!
0&
00
0:
0A
0K
#775000000
1!
1"
1&
1'
b001 *
10
11
1:
1;
b001 >
b001 ?
b001 @
1A
1B
b001 E
b001 G
b0 H
1K
1L
#780000000
0!
0&
00
0:
0A
0K
#785000000
1!
1&
10
1:
1A
1K
#790000000
0!
0&
00
0:
0A
0K
#795000000
1!
0"
1&
0'
10
01
1:
0;
1A
0B
1K
0L
#800000000
0!
0&
00
0:
0A
0K
#805000000
1!
1&
10
1:
1A
1K
#810000000
0!
0&
00
0:
0A
0K
#815000000
1!
1&
10
1:
1A
1K
#820000000
0!
0&
00
0:
0A
0K
#825000000
1!
1&
10
1:
1A
1K
#830000000
0!
0&
00
0:
0A
0K
#835000000
1!
1&
10
1:
1A
1K
#840000000
0!
0&
00
0:
0A
0K
#845000000
1!
1&
10
1:
1A
1K
#850000000
0!
0&
00
0:
0A
0K
#855000000
1!
1#
1&
1(
1+
1,
10
12
13
16
19
1:
1<
1=
1A
1D
1K
#860000000
0!
0&
00
0:
0A
0K
#865000000
1!
0#
1&
0(
0+
0,
1-
10
02
03
06
17
09
1:
0<
0=
b100 ?
1A
1C
0D
1K
#870000000
0!
0&
00
0:
0A
0K
#875000000
1!
1&
10
17
1:
1A
1I
1J
1K
#880000000
0!
0&
00
0:
0A
0K
#885000000
1!
1&
10
17
1:
1A
b010 G
b1 H
1K
#890000000
0!
0&
00
0:
0A
0K
#895000000
1!
1&
10
17
1:
1A
b101 G
b10 H
1K
#900000000
0!
0&
00
0:
0A
0K
#905000000
1!
1&
10
17
1:
1A
b011 G
b11 H
1K
#910000000
0!
0&
00
0:
0A
0K
#915000000
1!
1&
10
17
1:
1A
b111 G
b100 H
1K
#920000000
0!
0&
00
0:
0A
0K
#925000000
1!
1&
10
17
1:
1A
b110 G
b101 H
1K
#930000000
0!
0&
00
0:
0A
0K
#935000000
1!
1&
10
17
1:
1A
b100 G
b110 H
1K
#940000000
0!
0&
00
0:
0A
0K
#945000000
1!
1&
1.
10
14
17
1:
1A
1F
b001 G
0I
1K
1M
#950000000
0!
0&
00
0:
0A
0K
#955000000
1!
1&
0.
1/
10
04
15
17
1:
1A
0F
1K
0M
1N
b100 O
1P
b100 Q
#960000000
0!
0&
00
0:
0A
0K
#965000000
1!
1&
0-
0/
10
05
07
1:
1A
0C
1K
0N
0P
#970000000
0!
0&
00
0:
0A
0K
#975000000
1!
1$
1&
1)
1+
10
13
18
1:
1=
1A
0J
1K
#980000000
0!
0&
00
0:
0A
0K
#985000000
1!
0$
1&
0)
0+
10
03
08
1:
0=
b110 ?
1A
1K
#990000000
0!
0&
00
0:
0A
0K
#995000000
1!
1&
10
1:
1A
1K
#1000000000
0!
0&
00
0:
0A
0K
#1005000000
1!
1&
10
1:
1A
1K
#1010000000
0!
0&
00
0:
0A
0K
#1015000000
1!
1&
10
1:
1A
1K
#1020000000
0!
0&
00
0:
0A
0K
#1025000000
1!
1&
10
1:
1A
1K
#1030000000
0!
0&
00
0:
0A
0K
#1035000000
1!
1&
10
1:
1A
1K
#1040000000
0!
0&
00
0:
0A
0K
#1045000000
1!
1&
10
1:
1A
1K
#1050000000
0!
0&
00
0:
0A
0K
#1055000000
1!
1&
10
1:
1A
1K
#1060000000
0!
0&
00
0:
0A
0K
#1065000000
1!
1&
10
1:
1A
1K
#1070000000
0!
0&
00
0:
0A
0K
#1075000000
1!
1&
10
1:
1A
1K
#1080000000
0!
0&
00
0:
0A
0K
#1085000000
1!
1#
1&
1(
1+
1,
10
12
13
16
19
1:
1<
1=
1A
1D
1K
#1090000000
0!
0&
00
0:
0A
0K
#1095000000
1!
0#
1&
0(
b110 *
0+
0,
1-
10
02
03
06
17
09
1:
0<
0=
b110 >
b111 ?
b110 @
1A
1C
0D
b110 E
1K
#1100000000
0!
0&
00
0:
0A
0K
#1105000000
1!
1&
10
17
1:
1A
b0 H
1I
1J
1K
#1110000000
0!
0&
00
0:
0A
0K
#1115000000
1!
1&
10
17
1:
1A
b010 G
b1 H
1K
#1120000000
0!
0&
00
0:
0A
0K
#1125000000
1!
1&
10
17
1:
1A
b101 G
b10 H
1K
#1130000000
0!
0&
00
0:
0A
0K
#1135000000
1!
1&
10
17
1:
1A
b011 G
b11 H
1K
#1140000000
0!
0&
00
0:
0A
0K
#1145000000
1!
1&
10
17
1:
1A
b111 G
b100 H
1K
#1150000000
0!
0&
00
0:
0A
0K
#1155000000
1!
1&
10
17
1:
1A
b110 G
b101 H
1K
#1160000000
0!
0&
00
0:
0A
0K
#1165000000
1!
1&
10
17
1:
1A
b100 G
b110 H
1K
#1170000000
0!
0&
00
0:
0A
0K
#1175000000
1!
1&
1.
10
14
17
1:
1A
1F
b001 G
0I
1K
1M
#1180000000
0!
0&
00
0:
0A
0K
#1185000000
1!
1&
0.
1/
10
04
15
17
1:
1A
0F
1K
0M
1N
b101 O
1P
b101 Q
#1190000000
0!
0&
00
0:
0A
0K
#1195000000
1!
1&
0-
0/
10
05
07
1:
1A
0C
1K
0N
0P
#1200000000
0!
0&
00
0:
0A
0K
#1205000000
1!
1$
1&
1)
1+
10
13
18
1:
1=
1A
0J
1K
#1210000000
0!
0&
00
0:
0A
0K
