Input.vhdl
library IEEE;
use IEEE.STD_LOGIC_1164.ALL;
use IEEE.NUMERIC_STD.ALL;

entity Input is
    Port (
        clk : in STD_LOGIC;
        reset : in STD_LOGIC;
        inicia_Input : in STD_LOGIC;
        sw : in STD_LOGIC_VECTOR(6 downto 0);
        ativado : out STD_LOGIC_VECTOR(2 downto 0)
    );
end Input;

architecture Behavioral of Input is
    signal sw_anterior : STD_LOGIC_VECTOR(6 downto 0) := (others => '0');
    signal sw_atual : STD_LOGIC_VECTOR(6 downto 0) := (others => '0');
    
begin
    process(clk, reset)
    begin
        if reset = '1' then
            sw_anterior <= (others => '0');
            sw_atual <= (others => '0');
            ativado <= "000";
            
        elsif rising_edge(clk) then
            if inicia_Input = '1' then
                -- Atualiza registradores
                sw_anterior <= sw_atual;
                sw_atual <= sw;
                
                -- Detecta QUALQUER mudança e identifica qual switch foi ativado
                if (sw_atual /= sw_anterior) then
                    -- Verifica qual bit mudou de 0 para 1
                    for i in 0 to 6 loop
                        if sw_atual(i) = '1' and sw_anterior(i) = '0' then
                            -- Converte posição do switch para código 3 bits
                            case i is
                                when 0 => ativado <= "001";  -- SW0
                                when 1 => ativado <= "010";  -- SW1
                                when 2 => ativado <= "011";  -- SW2
                                when 3 => ativado <= "100";  -- SW3
                                when 4 => ativado <= "101";  -- SW4
                                when 5 => ativado <= "110";  -- SW5
                                when 6 => ativado <= "111";  -- SW6
                                when others => ativado <= "000";
                            end case;
                            exit;  -- Pega apenas o primeiro switch ativado
                        end if;
                    end loop;
                else
                    ativado <= "000";  -- Nenhuma mudança
                end if;
            else
                -- Reset quando não está capturando
                ativado <= "000";
                sw_anterior <= (others => '0');
                sw_atual <= (others => '0');
            end if;
        end if;
    end process;

end Behavioral;

tb_Input.vhdl
library IEEE;
use IEEE.STD_LOGIC_1164.ALL;
use IEEE.NUMERIC_STD.ALL;

entity tb_Input is
end tb_Input;

architecture Behavioral of tb_Input is
    component Input
        Port (
            clk : in STD_LOGIC;
            reset : in STD_LOGIC;
            inicia_Input : in STD_LOGIC;
            sw : in STD_LOGIC_VECTOR(6 downto 0);
            ativado : out STD_LOGIC_VECTOR(2 downto 0)
        );
    end component;
    
    signal clk : STD_LOGIC := '0';
    signal reset : STD_LOGIC := '1';
    signal inicia_Input : STD_LOGIC := '0';
    signal sw : STD_LOGIC_VECTOR(6 downto 0) := (others => '0');
    signal ativado : STD_LOGIC_VECTOR(2 downto 0);
    
    constant CLK_PERIOD : time := 10 ns;
    
begin
    dut: Input
    port map (
        clk => clk,
        reset => reset,
        inicia_Input => inicia_Input,
        sw => sw,
        ativado => ativado
    );
    
    -- Clock
    clk <= not clk after CLK_PERIOD/2;
    
    process
    begin
        -- Reset
        reset <= '1';
        wait for 50 ns;
        reset <= '0';
        inicia_Input <= '1';
        wait for 50 ns;
        
        -- Teste 1: Ativa SW0
        report "=== Teste 1: Ativando SW0 ===";
        sw <= "0000001";  -- SW0
        wait for 50 ns;
        report "Ativado = " & integer'image(to_integer(unsigned(ativado)));
        
        -- Teste 2: Ativa SW3 (mantém SW0)
        report "=== Teste 2: Ativando SW3 ===";
        sw <= "0001001";  -- SW0 + SW3
        wait for 50 ns;
        report "Ativado = " & integer'image(to_integer(unsigned(ativado)));
        
        -- Teste 3: Ativa SW6 (mantém anteriores)
        report "=== Teste 3: Ativando SW6 ===";
        sw <= "1001001";  -- SW0 + SW3 + SW6
        wait for 50 ns;
        report "Ativado = " & integer'image(to_integer(unsigned(ativado)));
        
        -- Teste 4: Mantém o mesmo estado - não deve detectar nada
        report "=== Teste 4: Mantendo estado ===";
        sw <= "1001001";  -- Mesmo estado
        wait for 50 ns;
        report "Ativado = " & integer'image(to_integer(unsigned(ativado)));
        
        -- Teste 5: Ativa SW1
        report "=== Teste 5: Ativando SW1 ===";
        sw <= "1001011";  -- SW0 + SW1 + SW3 + SW6
        wait for 50 ns;
        report "Ativado = " & integer'image(to_integer(unsigned(ativado)));
        
        -- Teste 6: Desativa captura
        report "=== Teste 6: Desativando captura ===";
        inicia_Input <= '0';
        wait for 50 ns;
        report "Ativado = " & integer'image(to_integer(unsigned(ativado)));
        
        wait for 100 ns;
        assert false report "=== Teste Input concluido ===" severity note;
        wait;
    end process;
end Behavioral;

wave_input.vcd
$date
  Fri Nov 14 18:23:43 2025
$end
$version
  GHDL v0
$end
$timescale
  1 fs
$end
$scope module standard $end
$upscope $end
$scope module std_logic_1164 $end
$upscope $end
$scope module numeric_std $end
$upscope $end
$scope module tb_input $end
$var reg 1 ! clk $end
$var reg 1 " reset $end
$var reg 1 # inicia_input $end
$var reg 7 $ sw[6:0] $end
$var reg 3 % ativado[2:0] $end
$scope module dut $end
$var reg 1 & clk $end
$var reg 1 ' reset $end
$var reg 1 ( inicia_input $end
$var reg 7 ) sw[6:0] $end
$var reg 3 * ativado[2:0] $end
$var reg 7 + sw_anterior[6:0] $end
$var reg 7 , sw_atual[6:0] $end
$upscope $end
$upscope $end
$enddefinitions $end
#0
0!
1"
0#
b0000000 $
b000 %
0&
1'
0(
b0000000 )
b000 *
b0000000 +
b0000000 ,
#5000000
1!
1&
#10000000
0!
0&
#15000000
1!
1&
#20000000
0!
0&
#25000000
1!
1&
#30000000
0!
0&
#35000000
1!
1&
#40000000
0!
0&
#45000000
1!
1&
#50000000
0!
0"
1#
0&
0'
1(
#55000000
1!
1&
#60000000
0!
0&
#65000000
1!
1&
#70000000
0!
0&
#75000000
1!
1&
#80000000
0!
0&
#85000000
1!
1&
#90000000
0!
0&
#95000000
1!
1&
#100000000
0!
b0000001 $
0&
b0000001 )
#105000000
1!
1&
b0000001 ,
#110000000
0!
0&
#115000000
1!
b001 %
1&
b001 *
b0000001 +
#120000000
0!
0&
#125000000
1!
b000 %
1&
b000 *
#130000000
0!
0&
#135000000
1!
1&
#140000000
0!
0&
#145000000
1!
1&
#150000000
0!
b0001001 $
0&
b0001001 )
#155000000
1!
1&
b0001001 ,
#160000000
0!
0&
#165000000
1!
b100 %
1&
b100 *
b0001001 +
#170000000
0!
0&
#175000000
1!
b000 %
1&
b000 *
#180000000
0!
0&
#185000000
1!
1&
#190000000
0!
0&
#195000000
1!
1&
#200000000
0!
b1001001 $
0&
b1001001 )
#205000000
1!
1&
b1001001 ,
#210000000
0!
0&
#215000000
1!
b111 %
1&
b111 *
b1001001 +
#220000000
0!
0&
#225000000
1!
b000 %
1&
b000 *
#230000000
0!
0&
#235000000
1!
1&
#240000000
0!
0&
#245000000
1!
1&
#250000000
0!
0&
#255000000
1!
1&
#260000000
0!
0&
#265000000
1!
1&
#270000000
0!
0&
#275000000
1!
1&
#280000000
0!
0&
#285000000
1!
1&
#290000000
0!
0&
#295000000
1!
1&
#300000000
0!
b1001011 $
0&
b1001011 )
#305000000
1!
1&
b1001011 ,
#310000000
0!
0&
#315000000
1!
b010 %
1&
b010 *
b1001011 +
#320000000
0!
0&
#325000000
1!
b000 %
1&
b000 *
#330000000
0!
0&
#335000000
1!
1&
#340000000
0!
0&
#345000000
1!
1&
#350000000
0!
0#
0&
0(
#355000000
1!
1&
b0000000 +
b0000000 ,
